{
"Tav 4.3":[
 null,
 {
  "Tavola 4.3 - Biblioteche per consistenza del patrimonio librario e regione - Anno 2013 (a)": "REGIONI",
  "Column2": "Non indicato",
  "Column3": "Fino a 2.000 volumi",
  "Column4": "Da 2.001\na 5.000",
  "Column5": "Da 5.001 \na 10.000",
  "Column6": "Da 10.001\na 100.000",
  "Column7": "Da 100.001 \na 500.000",
  "Column8": "Da 500.001  a 1.000.000",
  "Column9": "Oltre 1.000.000 \ndi volumi",
  "Column10": "Totale"
 },
 null,
 {
  "Tavola 4.3 - Biblioteche per consistenza del patrimonio librario e regione - Anno 2013 (a)": "Piemonte",
  "Column2": 79,
  "Column3": 253,
  "Column4": 326,
  "Column5": 142,
  "Column6": 245,
  "Column7": 24,
  "Column8": 1,
  "Column9": "-",
  "Column10": 1070
 },
 {
  "Tavola 4.3 - Biblioteche per consistenza del patrimonio librario e regione - Anno 2013 (a)": "Valle d'Aosta\/Vallée d'Aoste",
  "Column2": 4,
  "Column3": 3,
  "Column4": 19,
  "Column5": 19,
  "Column6": 10,
  "Column7": 1,
  "Column8": "-",
  "Column9": "-",
  "Column10": 56
 },
 {
  "Tavola 4.3 - Biblioteche per consistenza del patrimonio librario e regione - Anno 2013 (a)": "Liguria",
  "Column2": 79,
  "Column3": 83,
  "Column4": 76,
  "Column5": 68,
  "Column6": 86,
  "Column7": 9,
  "Column8": 1,
  "Column9": "-",
  "Column10": 402
 },
 {
  "Tavola 4.3 - Biblioteche per consistenza del patrimonio librario e regione - Anno 2013 (a)": "Lombardia",
  "Column2": 139,
  "Column3": 300,
  "Column4": 439,
  "Column5": 472,
  "Column6": 760,
  "Column7": 35,
  "Column8": 7,
  "Column9": 2,
  "Column10": 2154
 },
 {
  "Tavola 4.3 - Biblioteche per consistenza del patrimonio librario e regione - Anno 2013 (a)": "Trentino-Alto Adige",
  "Column2": 36,
  "Column3": 75,
  "Column4": 111,
  "Column5": 76,
  "Column6": 91,
  "Column7": 9,
  "Column8": "-",
  "Column9": 1,
  "Column10": 399
 },
 {
  "Tavola 4.3 - Biblioteche per consistenza del patrimonio librario e regione - Anno 2013 (a)": "Bolzano\/Bozen",
  "Column2": 3,
  "Column3": 57,
  "Column4": 93,
  "Column5": 44,
  "Column6": 22,
  "Column7": 4,
  "Column8": "-",
  "Column9": "-",
  "Column10": 223
 },
 {
  "Tavola 4.3 - Biblioteche per consistenza del patrimonio librario e regione - Anno 2013 (a)": "Trento",
  "Column2": 33,
  "Column3": 18,
  "Column4": 18,
  "Column5": 32,
  "Column6": 69,
  "Column7": 5,
  "Column8": "-",
  "Column9": 1,
  "Column10": 176
 },
 {
  "Tavola 4.3 - Biblioteche per consistenza del patrimonio librario e regione - Anno 2013 (a)": "Veneto",
  "Column2": 43,
  "Column3": 70,
  "Column4": 130,
  "Column5": 209,
  "Column6": 416,
  "Column7": 27,
  "Column8": 2,
  "Column9": 1,
  "Column10": 898
 },
 {
  "Tavola 4.3 - Biblioteche per consistenza del patrimonio librario e regione - Anno 2013 (a)": "Friuli-Venezia Giulia",
  "Column2": 26,
  "Column3": 53,
  "Column4": 108,
  "Column5": 92,
  "Column6": 92,
  "Column7": 9,
  "Column8": "-",
  "Column9": "-",
  "Column10": 380
 },
 {
  "Tavola 4.3 - Biblioteche per consistenza del patrimonio librario e regione - Anno 2013 (a)": "Emilia Romagna",
  "Column2": 60,
  "Column3": 181,
  "Column4": 204,
  "Column5": 198,
  "Column6": 379,
  "Column7": 29,
  "Column8": 5,
  "Column9": 2,
  "Column10": 1058
 },
 {
  "Tavola 4.3 - Biblioteche per consistenza del patrimonio librario e regione - Anno 2013 (a)": "Toscana",
  "Column2": 71,
  "Column3": 147,
  "Column4": 206,
  "Column5": 167,
  "Column6": 324,
  "Column7": 30,
  "Column8": 2,
  "Column9": 2,
  "Column10": 949
 },
 {
  "Tavola 4.3 - Biblioteche per consistenza del patrimonio librario e regione - Anno 2013 (a)": "Umbria",
  "Column2": 10,
  "Column3": 107,
  "Column4": 62,
  "Column5": 42,
  "Column6": 52,
  "Column7": 4,
  "Column8": "-",
  "Column9": "-",
  "Column10": 277
 },
 {
  "Tavola 4.3 - Biblioteche per consistenza del patrimonio librario e regione - Anno 2013 (a)": "Marche",
  "Column2": 33,
  "Column3": 33,
  "Column4": 98,
  "Column5": 66,
  "Column6": 94,
  "Column7": 11,
  "Column8": 1,
  "Column9": "-",
  "Column10": 336
 },
 {
  "Tavola 4.3 - Biblioteche per consistenza del patrimonio librario e regione - Anno 2013 (a)": "Lazio",
  "Column2": 161,
  "Column3": 173,
  "Column4": 211,
  "Column5": 204,
  "Column6": 396,
  "Column7": 49,
  "Column8": 13,
  "Column9": 2,
  "Column10": 1209
 },
 {
  "Tavola 4.3 - Biblioteche per consistenza del patrimonio librario e regione - Anno 2013 (a)": "Abruzzo",
  "Column2": 42,
  "Column3": 88,
  "Column4": 38,
  "Column5": 23,
  "Column6": 43,
  "Column7": 6,
  "Column8": "-",
  "Column9": "-",
  "Column10": 240
 },
 {
  "Tavola 4.3 - Biblioteche per consistenza del patrimonio librario e regione - Anno 2013 (a)": "Molise",
  "Column2": 3,
  "Column3": 51,
  "Column4": 36,
  "Column5": 9,
  "Column6": 16,
  "Column7": "-",
  "Column8": "-",
  "Column9": "-",
  "Column10": 115
 },
 {
  "Tavola 4.3 - Biblioteche per consistenza del patrimonio librario e regione - Anno 2013 (a)": "Campania",
  "Column2": 69,
  "Column3": 267,
  "Column4": 190,
  "Column5": 141,
  "Column6": 207,
  "Column7": 16,
  "Column8": 1,
  "Column9": 1,
  "Column10": 892
 },
 {
  "Tavola 4.3 - Biblioteche per consistenza del patrimonio librario e regione - Anno 2013 (a)": "Puglia",
  "Column2": 66,
  "Column3": 139,
  "Column4": 142,
  "Column5": 96,
  "Column6": 168,
  "Column7": 11,
  "Column8": "-",
  "Column9": "-",
  "Column10": 622
 },
 {
  "Tavola 4.3 - Biblioteche per consistenza del patrimonio librario e regione - Anno 2013 (a)": "Basilicata",
  "Column2": 18,
  "Column3": 27,
  "Column4": 40,
  "Column5": 27,
  "Column6": 11,
  "Column7": 2,
  "Column8": "-",
  "Column9": "-",
  "Column10": 125
 },
 {
  "Tavola 4.3 - Biblioteche per consistenza del patrimonio librario e regione - Anno 2013 (a)": "Calabria",
  "Column2": 42,
  "Column3": 131,
  "Column4": 95,
  "Column5": 61,
  "Column6": 59,
  "Column7": 7,
  "Column8": "-",
  "Column9": "-",
  "Column10": 395
 },
 {
  "Tavola 4.3 - Biblioteche per consistenza del patrimonio librario e regione - Anno 2013 (a)": "Sicilia  ",
  "Column2": 81,
  "Column3": 154,
  "Column4": 246,
  "Column5": 153,
  "Column6": 226,
  "Column7": 18,
  "Column8": 3,
  "Column9": "-",
  "Column10": 881
 },
 {
  "Tavola 4.3 - Biblioteche per consistenza del patrimonio librario e regione - Anno 2013 (a)": "Sardegna",
  "Column2": 28,
  "Column3": 90,
  "Column4": 154,
  "Column5": 116,
  "Column6": 81,
  "Column7": 8,
  "Column8": 1,
  "Column9": "-",
  "Column10": 478
 },
 null,
 {
  "Tavola 4.3 - Biblioteche per consistenza del patrimonio librario e regione - Anno 2013 (a)": "ITALIA",
  "Column2": 1090,
  "Column3": 2425,
  "Column4": 2931,
  "Column5": 2381,
  "Column6": 3756,
  "Column7": 305,
  "Column8": 37,
  "Column9": 11,
  "Column10": 12936
 },
 {
  "Tavola 4.3 - Biblioteche per consistenza del patrimonio librario e regione - Anno 2013 (a)": "Nord",
  "Column2": 466,
  "Column3": 1018,
  "Column4": 1413,
  "Column5": 1276,
  "Column6": 2079,
  "Column7": 143,
  "Column8": 16,
  "Column9": 6,
  "Column10": 6417
 },
 {
  "Tavola 4.3 - Biblioteche per consistenza del patrimonio librario e regione - Anno 2013 (a)": "Centro",
  "Column2": 275,
  "Column3": 460,
  "Column4": 577,
  "Column5": 479,
  "Column6": 866,
  "Column7": 94,
  "Column8": 16,
  "Column9": 4,
  "Column10": 2771
 },
 {
  "Tavola 4.3 - Biblioteche per consistenza del patrimonio librario e regione - Anno 2013 (a)": "Mezzogiorno",
  "Column2": 349,
  "Column3": 947,
  "Column4": 941,
  "Column5": 626,
  "Column6": 811,
  "Column7": 68,
  "Column8": 5,
  "Column9": 1,
  "Column10": 3748
 }
],
"Tav 4.4":[
 null,
 {
  "Tavola 4.4 - Biblioteche per tipologia funzionale e regione - Anno 2013 (a)": "REGIONI",
  "Column2": "Nazionali",
  "Column3": "Istituzioni scolastiche",
  "Column4": "Istituti d'istruzione superiore",
  "Column5": "Pubbliche",
  "Column6": "Speciali",
  "Column7": "Importanti non specializzate",
  "Column8": "Totale"
 },
 null,
 {
  "Tavola 4.4 - Biblioteche per tipologia funzionale e regione - Anno 2013 (a)": "Piemonte",
  "Column2": "-",
  "Column3": 19,
  "Column4": 88,
  "Column5": 598,
  "Column6": 330,
  "Column7": 35,
  "Column8": 1070
 },
 {
  "Tavola 4.4 - Biblioteche per tipologia funzionale e regione - Anno 2013 (a)": "Valle d'Aosta\/Vallée d'Aoste",
  "Column2": "-",
  "Column3": "-",
  "Column4": 1,
  "Column5": 45,
  "Column6": 8,
  "Column7": 2,
  "Column8": 56
 },
 {
  "Tavola 4.4 - Biblioteche per tipologia funzionale e regione - Anno 2013 (a)": "Liguria",
  "Column2": "-",
  "Column3": 19,
  "Column4": 86,
  "Column5": 141,
  "Column6": 123,
  "Column7": 33,
  "Column8": 402
 },
 {
  "Tavola 4.4 - Biblioteche per tipologia funzionale e regione - Anno 2013 (a)": "Lombardia",
  "Column2": "-",
  "Column3": 14,
  "Column4": 224,
  "Column5": 777,
  "Column6": 566,
  "Column7": 573,
  "Column8": 2154
 },
 {
  "Tavola 4.4 - Biblioteche per tipologia funzionale e regione - Anno 2013 (a)": "Trentino-Alto Adige",
  "Column2": "-",
  "Column3": "-",
  "Column4": 3,
  "Column5": 248,
  "Column6": 83,
  "Column7": 65,
  "Column8": 399
 },
 {
  "Tavola 4.4 - Biblioteche per tipologia funzionale e regione - Anno 2013 (a)": "Bolzano\/Bozen",
  "Column2": "-",
  "Column3": "-",
  "Column4": 2,
  "Column5": 172,
  "Column6": 34,
  "Column7": 15,
  "Column8": 223
 },
 {
  "Tavola 4.4 - Biblioteche per tipologia funzionale e regione - Anno 2013 (a)": "Trento",
  "Column2": "-",
  "Column3": "-",
  "Column4": 1,
  "Column5": 76,
  "Column6": 49,
  "Column7": 50,
  "Column8": 176
 },
 {
  "Tavola 4.4 - Biblioteche per tipologia funzionale e regione - Anno 2013 (a)": "Veneto",
  "Column2": "-",
  "Column3": 5,
  "Column4": 87,
  "Column5": 585,
  "Column6": 162,
  "Column7": 59,
  "Column8": 898
 },
 {
  "Tavola 4.4 - Biblioteche per tipologia funzionale e regione - Anno 2013 (a)": "Friuli-Venezia Giulia",
  "Column2": "-",
  "Column3": 7,
  "Column4": 70,
  "Column5": 179,
  "Column6": 86,
  "Column7": 38,
  "Column8": 380
 },
 {
  "Tavola 4.4 - Biblioteche per tipologia funzionale e regione - Anno 2013 (a)": "Emilia Romagna",
  "Column2": "-",
  "Column3": 40,
  "Column4": 192,
  "Column5": 439,
  "Column6": 380,
  "Column7": 7,
  "Column8": 1058
 },
 {
  "Tavola 4.4 - Biblioteche per tipologia funzionale e regione - Anno 2013 (a)": "Toscana",
  "Column2": 1,
  "Column3": 15,
  "Column4": 170,
  "Column5": 303,
  "Column6": 408,
  "Column7": 52,
  "Column8": 949
 },
 {
  "Tavola 4.4 - Biblioteche per tipologia funzionale e regione - Anno 2013 (a)": "Umbria",
  "Column2": "-",
  "Column3": 3,
  "Column4": 105,
  "Column5": 58,
  "Column6": 73,
  "Column7": 38,
  "Column8": 277
 },
 {
  "Tavola 4.4 - Biblioteche per tipologia funzionale e regione - Anno 2013 (a)": "Marche",
  "Column2": "-",
  "Column3": 19,
  "Column4": 68,
  "Column5": 110,
  "Column6": 83,
  "Column7": 56,
  "Column8": 336
 },
 {
  "Tavola 4.4 - Biblioteche per tipologia funzionale e regione - Anno 2013 (a)": "Lazio",
  "Column2": 1,
  "Column3": 121,
  "Column4": 174,
  "Column5": 290,
  "Column6": 577,
  "Column7": 46,
  "Column8": 1209
 },
 {
  "Tavola 4.4 - Biblioteche per tipologia funzionale e regione - Anno 2013 (a)": "Abruzzo",
  "Column2": "-",
  "Column3": 12,
  "Column4": 13,
  "Column5": 150,
  "Column6": 43,
  "Column7": 22,
  "Column8": 240
 },
 {
  "Tavola 4.4 - Biblioteche per tipologia funzionale e regione - Anno 2013 (a)": "Molise",
  "Column2": "-",
  "Column3": "-",
  "Column4": 2,
  "Column5": 98,
  "Column6": 6,
  "Column7": 9,
  "Column8": 115
 },
 {
  "Tavola 4.4 - Biblioteche per tipologia funzionale e regione - Anno 2013 (a)": "Campania",
  "Column2": "-",
  "Column3": 39,
  "Column4": 183,
  "Column5": 346,
  "Column6": 261,
  "Column7": 63,
  "Column8": 892
 },
 {
  "Tavola 4.4 - Biblioteche per tipologia funzionale e regione - Anno 2013 (a)": "Puglia",
  "Column2": "-",
  "Column3": 32,
  "Column4": 154,
  "Column5": 217,
  "Column6": 137,
  "Column7": 82,
  "Column8": 622
 },
 {
  "Tavola 4.4 - Biblioteche per tipologia funzionale e regione - Anno 2013 (a)": "Basilicata",
  "Column2": "-",
  "Column3": 3,
  "Column4": 2,
  "Column5": 93,
  "Column6": 19,
  "Column7": 8,
  "Column8": 125
 },
 {
  "Tavola 4.4 - Biblioteche per tipologia funzionale e regione - Anno 2013 (a)": "Calabria",
  "Column2": "-",
  "Column3": 10,
  "Column4": 24,
  "Column5": 218,
  "Column6": 114,
  "Column7": 29,
  "Column8": 395
 },
 {
  "Tavola 4.4 - Biblioteche per tipologia funzionale e regione - Anno 2013 (a)": "Sicilia  ",
  "Column2": "-",
  "Column3": 32,
  "Column4": 236,
  "Column5": 345,
  "Column6": 150,
  "Column7": 118,
  "Column8": 881
 },
 {
  "Tavola 4.4 - Biblioteche per tipologia funzionale e regione - Anno 2013 (a)": "Sardegna",
  "Column2": "-",
  "Column3": 6,
  "Column4": 92,
  "Column5": 270,
  "Column6": 75,
  "Column7": 35,
  "Column8": 478
 },
 null,
 {
  "Tavola 4.4 - Biblioteche per tipologia funzionale e regione - Anno 2013 (a)": "ITALIA",
  "Column2": 2,
  "Column3": 396,
  "Column4": 1974,
  "Column5": 5510,
  "Column6": 3684,
  "Column7": 1370,
  "Column8": 12936
 },
 {
  "Tavola 4.4 - Biblioteche per tipologia funzionale e regione - Anno 2013 (a)": "Nord",
  "Column2": "-",
  "Column3": 104,
  "Column4": 751,
  "Column5": 3012,
  "Column6": 1738,
  "Column7": 812,
  "Column8": 6417
 },
 {
  "Tavola 4.4 - Biblioteche per tipologia funzionale e regione - Anno 2013 (a)": "Centro",
  "Column2": 2,
  "Column3": 158,
  "Column4": 517,
  "Column5": 761,
  "Column6": 1141,
  "Column7": 192,
  "Column8": 2771
 },
 {
  "Tavola 4.4 - Biblioteche per tipologia funzionale e regione - Anno 2013 (a)": "Mezzogiorno",
  "Column2": "-",
  "Column3": 134,
  "Column4": 706,
  "Column5": 1737,
  "Column6": 805,
  "Column7": 366,
  "Column8": 3748
 }
],
"Tav 4.6":[
 null,
 {
  "Tavola 4.6 - ": "TIPOLOGIA",
  "Column2": "Non indicato",
  "Column3": "Fino a 2.000 volumi",
  "Column4": "Da 2.001\na 5.000",
  "Column5": "Da 5.001\na 10.000",
  "Column6": "Da 10.001\na 100.000",
  "Column7": "Da 100.001\na 500.000",
  "Column8": "Da 500.001\na 1.000.000",
  "Column9": "Oltre 1.000.000 di volumi",
  "Column10": "Totale"
 },
 null,
 {
  "Tavola 4.6 - ": "Nazionali",
  "Column2": "-",
  "Column3": "-",
  "Column4": "-",
  "Column5": "-",
  "Column6": "-",
  "Column7": "-",
  "Column8": "-",
  "Column9": 2,
  "Column10": 2
 },
 {
  "Tavola 4.6 - ": "Istituzioni scolastiche",
  "Column2": 350,
  "Column3": 6,
  "Column4": 7,
  "Column5": 15,
  "Column6": 18,
  "Column7": "-",
  "Column8": "-",
  "Column9": "-",
  "Column10": 396
 },
 {
  "Tavola 4.6 - ": "Istituti d'istruzione superiore",
  "Column2": 186,
  "Column3": 461,
  "Column4": 362,
  "Column5": 290,
  "Column6": 598,
  "Column7": 70,
  "Column8": 5,
  "Column9": 2,
  "Column10": 1974
 },
 {
  "Tavola 4.6 - ": "Pubbliche",
  "Column2": 242,
  "Column3": 1176,
  "Column4": 1815,
  "Column5": 1394,
  "Column6": 844,
  "Column7": 33,
  "Column8": 4,
  "Column9": 2,
  "Column10": 5510
 },
 {
  "Tavola 4.6 - ": "Specializzate",
  "Column2": 288,
  "Column3": 763,
  "Column4": 729,
  "Column5": 618,
  "Column6": 1162,
  "Column7": 111,
  "Column8": 10,
  "Column9": 3,
  "Column10": 3684
 },
 {
  "Tavola 4.6 - ": "Importanti non specializzate",
  "Column2": 24,
  "Column3": 19,
  "Column4": 18,
  "Column5": 64,
  "Column6": 1134,
  "Column7": 91,
  "Column8": 18,
  "Column9": 2,
  "Column10": 1370
 },
 {
  "Tavola 4.6 - ": "Totale                 ",
  "Column2": 1090,
  "Column3": 2425,
  "Column4": 2931,
  "Column5": 2381,
  "Column6": 3756,
  "Column7": 305,
  "Column8": 37,
  "Column9": 11,
  "Column10": 12936
 }
]
}